teal/__init__.py
teal/auth.py
teal/cache.py
teal/cli.py
teal/client.py
teal/config.py
teal/db.py
teal/enums.py
teal/json_util.py
teal/marshmallow.py
teal/query.py
teal/request.py
teal/resource.py
teal/teal.py
teal/utils.py
tests/__init__.py
tests/conftest.py
tests/test_api_spec.py
tests/test_auth.py
tests/test_db.py
tests/test_enums.py
tests/test_marshmallow.py
tests/test_query.py
tests/test_resource.py
tests/test_resource_app.py
tests/test_testing.py
tests/test_utils.py
teal-0.2.0a41.dist-info/LICENSE
teal-0.2.0a41.dist-info/METADATA
teal-0.2.0a41.dist-info/WHEEL
teal-0.2.0a41.dist-info/top_level.txt
teal-0.2.0a41.dist-info/RECORD
